LICENSE
README.md
license.txt
setup.py
matplotlib_add_ons/__init__.py
matplotlib_add_ons/annotations.py
matplotlib_add_ons/ask_close.py
matplotlib_add_ons/choose_report_windows.py
matplotlib_add_ons/copy_axis_to_clipboard.py
matplotlib_add_ons/easy_animation.py
matplotlib_add_ons/misc_add_ons.py
matplotlib_add_ons/save_report_tool.py
matplotlib_add_ons/twinx_hover.py
mpl_add_ons.egg-info/PKG-INFO
mpl_add_ons.egg-info/SOURCES.txt
mpl_add_ons.egg-info/dependency_links.txt
mpl_add_ons.egg-info/requires.txt
mpl_add_ons.egg-info/top_level.txt
tests/tests.py