Metadata-Version: 2.1
Name: mpl-add-ons
Version: 0.0.11
Summary: Helper functions to make using matplotlib easier, more efficient and streamlined
Author: Ethan Blake
License-File: LICENSE
License-File: license.txt
